mynest/__init__.py
mynest/functions.py
nestle_mynest-2.9.2.dist-info/LICENSE.txt
nestle_mynest-2.9.2.dist-info/METADATA
nestle_mynest-2.9.2.dist-info/WHEEL
nestle_mynest-2.9.2.dist-info/top_level.txt
nestle_mynest-2.9.2.dist-info/RECORD
