Metadata-Version: 2.1
Name: nestle-mynest
Version: 2.9.2
Summary: Trial library for nesting and laser cutting
Home-page: https://github.com/KeepsakeAutomation/Functional-modules-for-Laser-Cutting-Nesting-
Author: HaShTi
Author-email: hashtishah@gmail.com
License: MIT
Platform: UNKNOWN
Classifier: License :: OSI Approved :: MIT License
Classifier: Programming Language :: Python :: 3
Requires-Dist: matplotlib
Requires-Dist: svglib
Requires-Dist: reportlab
Requires-Dist: pathlib
Requires-Dist: setuptools
